[{"n": "Abruzzo", "id": "Abruzzo", "v": 0.06281313093546699, "c": "yellow", "max": 709, "date": "06/02/21"}, {"n": "Basilicata", "id": "Basilicata", "v": 0.14840379637618636, "c": "yellow", "max": 545}, {"n": "Bolzano", "id": "Bolzano", "v": 0.029278713244533804, "c": "yellow", "max": 530}, {"n": "Calabria", "id": "Calabria", "v": 0.24685679239497088, "c": "yellow", "max": 1967}, {"n": "Campania", "id": "Campania", "v": 0.10447956460306662, "c": "yellow", "max": 6226}, {"n": "Emilia-Romagna", "id": "Emilia-Romagna", "v": 0.07114017530540409, "c": "yellow", "max": 3417}, {"n": "Friuli Venezia Giulia", "id": "Friuli Venezia Giulia", "v": 0.032246612626471806, "c": "yellow", "max": 406}, {"n": "Lazio", "id": "Lazio", "v": 0.10425740922654902, "c": "yellow", "max": 4542}, {"n": "Liguria", "id": "Liguria", "v": 0.04897881092457072, "c": "yellow", "max": 782}, {"n": "Lombardia", "id": "Lombardia", "v": 0.05485972369217882, "c": "yellow", "max": 7880}, {"n": "Marche", "id": "Marche", "v": 0.10368649123908812, "c": "yellow", "max": 1394}, {"n": "Molise", "id": "Molise", "v": 0.034670008354218886, "c": "yellow", "max": 61}, {"n": "Piemonte", "id": "Piemonte", "v": 0.05315103557759756, "c": "yellow", "max": 3514}, {"n": "Puglia", "id": "Puglia", "v": 0.10876278969841824, "c": "yellow", "max": 3312}, {"n": "Sardegna", "id": "Sardegna", "v": 0.059386767079074775, "c": "yellow", "max": 410}, {"n": "Sicilia", "id": "Sicilia", "v": 0.18588963839433817, "c": "yellow", "max": 4767}, {"n": "Toscana", "id": "Toscana", "v": 0.09481958284334963, "c": "yellow", "max": 3798}, {"n": "Trento", "id": "Trento", "v": 0.10110324386629344, "c": "yellow", "max": 435}, {"n": "Umbria", "id": "Umbria", "v": 0.05211141060197664, "c": "yellow", "max": 465}, {"n": "Valle d'Aosta", "id": "Valle d'Aosta", "v": 0.07630662020905923, "c": "yellow", "max": 176}, {"n": "Veneto", "id": "Veneto", "v": 0.03986689946607961, "c": "yellow", "max": 2443}]