[{"n": "Abruzzo", "id": "Abruzzo", "v": 0.030434457488970317, "c": "yellow", "max": 292, "date": "06/27/21"}, {"n": "Basilicata", "id": "Basilicata", "v": 0.06988783433994822, "c": "yellow", "max": 244}, {"n": "Bolzano", "id": "Bolzano", "v": 0.004565636257016001, "c": "yellow", "max": 95}, {"n": "Calabria", "id": "Calabria", "v": 0.09189410201369724, "c": "yellow", "max": 655}, {"n": "Campania", "id": "Campania", "v": 0.024085509445810872, "c": "yellow", "max": 1408}, {"n": "Emilia-Romagna", "id": "Emilia-Romagna", "v": 0.021792394230105594, "c": "yellow", "max": 874}, {"n": "Friuli Venezia Giulia", "id": "Friuli Venezia Giulia", "v": -0.0628956866457606, "c": "green", "max": 635}, {"n": "Lazio", "id": "Lazio", "v": 0.03130502474375846, "c": "yellow", "max": 1298}, {"n": "Liguria", "id": "Liguria", "v": 0.028220213325680397, "c": "yellow", "max": 350}, {"n": "Lombardia", "id": "Lombardia", "v": 0.01412667598634874, "c": "yellow", "max": 1975}, {"n": "Marche", "id": "Marche", "v": 0.01507253658230233, "c": "yellow", "max": 200}, {"n": "Molise", "id": "Molise", "v": 0.05012531328320802, "c": "yellow", "max": 81}, {"n": "Piemonte", "id": "Piemonte", "v": 0.009377422808550438, "c": "yellow", "max": 616}, {"n": "Puglia", "id": "Puglia", "v": 0.028681150468619923, "c": "yellow", "max": 958}, {"n": "Sardegna", "id": "Sardegna", "v": 0.02474448628294782, "c": "yellow", "max": 168}, {"n": "Sicilia", "id": "Sicilia", "v": 0.06563087470972023, "c": "yellow", "max": 1868}, {"n": "Toscana", "id": "Toscana", "v": 0.019496193600297085, "c": "yellow", "max": 729}, {"n": "Trento", "id": "Trento", "v": 0.014161040671826115, "c": "yellow", "max": 69}, {"n": "Umbria", "id": "Umbria", "v": 0.017561055296904354, "c": "yellow", "max": 166}, {"n": "Valle d'Aosta", "id": "Valle d'Aosta", "v": 0.013240418118466898, "c": "yellow", "max": 27}, {"n": "Veneto", "id": "Veneto", "v": 0.010729016422480326, "c": "yellow", "max": 679}]