[{"n": "Antwerpen, Flanders", "id": "Antwerpen, Flanders", "v": 0.23561463975053337, "c": "yellow", "max": 5222, "date": "12/19/20"}, {"n": "BrabantWallon, Wallonia", "id": "BrabantWallon, Wallonia", "v": 0.07465840259191436, "c": "yellow", "max": 814}, {"n": "Brussels, Brussels", "id": "Brussels, Brussels", "v": 0.06520371624891126, "c": "yellow", "max": 2005}, {"n": "Hainaut, Wallonia", "id": "Hainaut, Wallonia", "v": 0.08067944077308803, "c": "yellow", "max": 3829}, {"n": "Limburg, Flanders", "id": "Limburg, Flanders", "v": 0.28818652849740933, "c": "yellow", "max": 2068}, {"n": "Li\u00e8ge, Wallonia", "id": "Li\u00e8ge, Wallonia", "v": 0.048612364806092136, "c": "yellow", "max": 2259}, {"n": "Luxembourg, Wallonia", "id": "Luxembourg, Wallonia", "v": 0.12072517511330862, "c": "yellow", "max": 933}, {"n": "Namur, Wallonia", "id": "Namur, Wallonia", "v": 0.09758511480601742, "c": "yellow", "max": 1428}, {"n": "OostVlaanderen, Flanders", "id": "OostVlaanderen, Flanders", "v": 0.21966155264370843, "c": "yellow", "max": 4954}, {"n": "VlaamsBrabant, Flanders", "id": "VlaamsBrabant, Flanders", "v": 0.1126207366438219, "c": "yellow", "max": 2161}, {"n": "WestVlaanderen, Flanders", "id": "WestVlaanderen, Flanders", "v": 0.24777417634267423, "c": "yellow", "max": 4397}]