[{"n": "Burgenland", "id": "Burgenland", "v": 0.024977293369663943, "c": "yellow", "max": 70, "date": "06/24/21"}, {"n": "K\u00e4rnten", "id": "K\u00e4rnten", "v": 0.013535911602209945, "c": "yellow", "max": 150}, {"n": "NOT SPECIFIED", "id": "NOT SPECIFIED", "v": 0.0, "c": "green", "max": 0}, {"n": "Nieder\u00f6sterreich", "id": "Nieder\u00f6sterreich", "v": 0.03720230634244172, "c": "yellow", "max": 618}, {"n": "Ober\u00f6sterreich", "id": "Ober\u00f6sterreich", "v": 0.015085200746965455, "c": "yellow", "max": 458}, {"n": "Salzburg", "id": "Salzburg", "v": 0.013658869728529963, "c": "yellow", "max": 115}, {"n": "Steiermark", "id": "Steiermark", "v": 0.01371308016877637, "c": "yellow", "max": 272}, {"n": "Tirol", "id": "Tirol", "v": 0.022983894079211326, "c": "yellow", "max": 406}, {"n": "Vorarlberg", "id": "Vorarlberg", "v": 0.019656019656019656, "c": "yellow", "max": 180}, {"n": "Wien", "id": "Wien", "v": 0.04177797030298654, "c": "yellow", "max": 1215}]