[{"n": "Ayrshire and Arran", "id": "Ayrshire and Arran", "v": 0.01281657241209737, "c": "yellow", "max": 335, "date": "05/04/21"}, {"n": "Borders", "id": "Borders", "v": 0.001575078753937697, "c": "green", "max": 13}, {"n": "Dumfries and Galloway", "id": "Dumfries and Galloway", "v": 0.009365117976161517, "c": "yellow", "max": 47}, {"n": "East of England", "id": "East of England", "v": 0.006008838994299072, "c": "yellow", "max": 3448}, {"n": "Eileanan Siar (Western Isles)", "id": "Eileanan Siar (Western Isles)", "v": 0.0, "c": "green", "max": 0}, {"n": "England", "id": "England", "v": 0.06443979248202421, "c": "yellow", "max": 632}, {"n": "Fife", "id": "Fife", "v": 0.019000803516566623, "c": "yellow", "max": 432}, {"n": "Forth Valley", "id": "Forth Valley", "v": 0.01038994356080041, "c": "yellow", "max": 329}, {"n": "Grampian", "id": "Grampian", "v": 0.014192217400583339, "c": "yellow", "max": 433}, {"n": "Greater Glasgow and Clyde", "id": "Greater Glasgow and Clyde", "v": 0.009667065076036051, "c": "yellow", "max": 1486}, {"n": "Highland", "id": "Highland", "v": 0.009426312588688425, "c": "yellow", "max": 108}, {"n": "Lanarkshire", "id": "Lanarkshire", "v": 0.011471366544202655, "c": "yellow", "max": 964}, {"n": "London", "id": "London", "v": 0.005353297908065504, "c": "yellow", "max": 5720}, {"n": "Lothian", "id": "Lothian", "v": 0.011016221132952652, "c": "yellow", "max": 622}, {"n": "Midlands", "id": "Midlands", "v": 0.0062544929277520344, "c": "yellow", "max": 7502}, {"n": "NOT SPECIFIED", "id": "NOT SPECIFIED", "v": 0.0, "c": "green", "max": 0}, {"n": "North East and Yorkshire", "id": "North East and Yorkshire", "v": 0.009655071145888434, "c": "yellow", "max": 10052}, {"n": "North West", "id": "North West", "v": 0.005449172288795208, "c": "yellow", "max": 4955}, {"n": "Northern Ireland", "id": "Northern Ireland", "v": 0.0098659845313765, "c": "yellow", "max": 2266}, {"n": "Orkney", "id": "Orkney", "v": 0.014084507042253523, "c": "green", "max": 2}, {"n": "Scotland", "id": "Scotland", "v": 0.0, "c": "green", "max": 0}, {"n": "Shetland", "id": "Shetland", "v": 0.0, "c": "green", "max": 3}, {"n": "South East", "id": "South East", "v": 0.005617702494308863, "c": "yellow", "max": 4133}, {"n": "South West", "id": "South West", "v": 0.0068747925808473765, "c": "yellow", "max": 1729}, {"n": "Tayside", "id": "Tayside", "v": 0.010916011346906531, "c": "yellow", "max": 306}, {"n": "Wales", "id": "Wales", "v": 0.003277971502796129, "c": "yellow", "max": 1435}]