[{"n": "Alberta, Calgary, CA", "id": "4832", "v": 0.25755743651753327, "c": "yellow", "max": 3423, "date": "04/04/21"}, {"n": "Alberta, Central, CA", "id": "4833", "v": 0.17339373970345967, "c": "yellow", "max": 628}, {"n": "Alberta, Edmonton, CA", "id": "4834", "v": 0.09924525028194672, "c": "yellow", "max": 1552}, {"n": "Alberta, North, CA", "id": "4835", "v": 0.27042454513021763, "c": "yellow", "max": 926}, {"n": "Alberta, South, CA", "id": "4831", "v": 0.41146278870829767, "c": "orange", "max": 707}, {"n": "BC, Fraser, CA", "id": "5921", "v": 0.76168404789494, "c": "orange", "max": 6135}, {"n": "BC, Interior, CA", "id": "5911", "v": 0.6617038875103392, "c": "orange", "max": 771}, {"n": "BC, Island, CA", "id": "5941", "v": 0.8368298368298368, "c": "red", "max": 653}, {"n": "BC, Northern, CA", "id": "5951", "v": 0.5896168108776266, "c": "orange", "max": 649}, {"n": "BC, Vancouver Coastal, CA", "id": "5931", "v": 0.8357487922705314, "c": "red", "max": 3966}, {"n": "Manitoba, Interlake-Eastern, CA", "id": "4603", "v": 0.02434077079107505, "c": "yellow", "max": 18}, {"n": "Manitoba, Northern, CA", "id": "4604", "v": 0.27833182230281045, "c": "yellow", "max": 400}, {"n": "Manitoba, Prairie Mountain, CA", "id": "4602", "v": 0.15957446808510636, "c": "yellow", "max": 56}, {"n": "Manitoba, Southern Health, CA", "id": "4605", "v": 0.022177419354838707, "c": "yellow", "max": 56}, {"n": "Manitoba, Winnipeg, CA", "id": "4601", "v": 0.11058230683090706, "c": "yellow", "max": 470}, {"n": "NL, Central, CA", "id": "1012", "v": 0.16666666666666666, "c": "green", "max": 2}, {"n": "NL, Eastern, CA", "id": "1011", "v": 0.007339449541284403, "c": "green", "max": 3}, {"n": "NL, Labrador-Grenfell, CA", "id": "1014", "v": 0.0, "c": "green", "max": 0}, {"n": "NL, Western, CA", "id": "1013", "v": 0.09999999999999999, "c": "green", "max": 1}, {"n": "NWT, NWT, CA", "id": "6101", "v": 0.0, "c": "green", "max": 0}, {"n": "New Brunswick, Zone 1 (Moncton area), CA", "id": "1301", "v": 0.11494252873563218, "c": "green", "max": 11}, {"n": "New Brunswick, Zone 2 (Saint John area), CA", "id": "1302", "v": 0.09615384615384616, "c": "green", "max": 11}, {"n": "New Brunswick, Zone 3 (Fredericton area), CA", "id": "1303", "v": 0.043478260869565216, "c": "green", "max": 3}, {"n": "New Brunswick, Zone 4 (Edmundston area), CA", "id": "1304", "v": 0.5598086124401914, "c": "orange", "max": 135}, {"n": "New Brunswick, Zone 5 (Campbellton area), CA", "id": "1305", "v": 0.0, "c": "green", "max": 0}, {"n": "New Brunswick, Zone 6 (Bathurst area), CA", "id": "1306", "v": 0.0, "c": "green", "max": 1}, {"n": "New Brunswick, Zone 7 (Miramichi area), CA", "id": "1307", "v": 0.0, "c": "green", "max": 1}, {"n": "Nova Scotia, Zone 1 - Western, CA", "id": "1201", "v": 0.5365853658536586, "c": "green", "max": 11}, {"n": "Nova Scotia, Zone 2 - Northern, CA", "id": "1202", "v": 0.04651162790697674, "c": "green", "max": 1}, {"n": "Nova Scotia, Zone 3 - Eastern, CA", "id": "1203", "v": 0.23529411764705882, "c": "green", "max": 6}, {"n": "Nova Scotia, Zone 4 - Central, CA", "id": "1204", "v": 0.052173913043478265, "c": "yellow", "max": 33}, {"n": "Ontario, Algoma, CA", "id": "3526", "v": 0.2127659574468085, "c": "yellow", "max": 16}, {"n": "Ontario, Brant, CA", "id": "3527", "v": 0.6473829201101928, "c": "orange", "max": 189}, {"n": "Ontario, Chatham-Kent, CA", "id": "3540", "v": 0.3550724637681159, "c": "yellow", "max": 136}, {"n": "Ontario, Durham, CA", "id": "3530", "v": 0.771488469601677, "c": "orange", "max": 1777}, {"n": "Ontario, Eastern, CA", "id": "3558", "v": 0.33421052631578946, "c": "yellow", "max": 363}, {"n": "Ontario, Grey Bruce, CA", "id": "3533", "v": 0.7886178861788617, "c": "orange", "max": 104}, {"n": "Ontario, Haldimand-Norfolk, CA", "id": "3534", "v": 0.3544668587896254, "c": "yellow", "max": 147}, {"n": "Ontario, Haliburton Kawartha Pineridge, CA", "id": "3535", "v": 0.5679611650485438, "c": "orange", "max": 87}, {"n": "Ontario, Halton, CA", "id": "3536", "v": 0.6165458937198067, "c": "orange", "max": 913}, {"n": "Ontario, Hamilton, CA", "id": "3537", "v": 0.7267050912584053, "c": "orange", "max": 1454}, {"n": "Ontario, Hastings Prince Edward, CA", "id": "3538", "v": 0.9611650485436893, "c": "red", "max": 131}, {"n": "Ontario, Huron Perth, CA", "id": "3539", "v": 0.09523809523809523, "c": "yellow", "max": 29}, {"n": "Ontario, Kingston Frontenac Lennox & Addington, CA", "id": "3541", "v": 0.4257425742574258, "c": "orange", "max": 125}, {"n": "Ontario, Lambton, CA", "id": "3542", "v": 0.3713527851458886, "c": "yellow", "max": 345}, {"n": "Ontario, Leeds Grenville and Lanark, CA", "id": "3543", "v": 0.3129251700680272, "c": "yellow", "max": 213}, {"n": "Ontario, Middlesex-London, CA", "id": "3544", "v": 0.6008454106280193, "c": "orange", "max": 830}, {"n": "Ontario, Niagara, CA", "id": "3546", "v": 0.40216998191681735, "c": "orange", "max": 907}, {"n": "Ontario, North Bay Parry Sound, CA", "id": "3547", "v": 0.16666666666666666, "c": "green", "max": 16}, {"n": "Ontario, Northwestern, CA", "id": "3549", "v": 0.24793388429752067, "c": "yellow", "max": 65}, {"n": "Ontario, Ottawa, CA", "id": "3551", "v": 0.9493670886075949, "c": "red", "max": 1916}, {"n": "Ontario, Peel, CA", "id": "3553", "v": 0.7948135755258127, "c": "red", "max": 6032}, {"n": "Ontario, Peterborough, CA", "id": "3555", "v": 0.8486842105263157, "c": "red", "max": 105}, {"n": "Ontario, Porcupine, CA", "id": "3556", "v": 0.2657342657342658, "c": "yellow", "max": 23}, {"n": "Ontario, Renfrew, CA", "id": "3557", "v": 0.25, "c": "yellow", "max": 45}, {"n": "Ontario, Simcoe Muskoka, CA", "id": "3560", "v": 0.4291115311909263, "c": "orange", "max": 609}, {"n": "Ontario, Southwestern, CA", "id": "3575", "v": 0.1820689655172414, "c": "yellow", "max": 164}, {"n": "Ontario, Sudbury, CA", "id": "3561", "v": 0.4924078091106291, "c": "orange", "max": 311}, {"n": "Ontario, Thunder Bay, CA", "id": "3562", "v": 0.27503015681544024, "c": "yellow", "max": 286}, {"n": "Ontario, Timiskaming, CA", "id": "3563", "v": 0.11999999999999998, "c": "green", "max": 14}, {"n": "Ontario, Toronto, CA", "id": "3595", "v": 0.7401574803149606, "c": "orange", "max": 10557}, {"n": "Ontario, Waterloo, CA", "id": "3565", "v": 0.2532133676092545, "c": "yellow", "max": 622}, {"n": "Ontario, Wellington Dufferin Guelph, CA", "id": "3566", "v": 0.22660653889515223, "c": "yellow", "max": 249}, {"n": "Ontario, Windsor-Essex, CA", "id": "3568", "v": 0.15838612870956986, "c": "yellow", "max": 433}, {"n": "Ontario, York, CA", "id": "3570", "v": 0.737915407854985, "c": "orange", "max": 3708}, {"n": "PEI, Prince Edward Island, CA", "id": "1100", "v": 0.1951219512195122, "c": "green", "max": 12}, {"n": "Quebec, Abitibi-T\u00e9miscamingue, CA", "id": "2408", "v": 0.3224852071005917, "c": "yellow", "max": 99}, {"n": "Quebec, Bas-Saint-Laurent, CA", "id": "2401", "v": 0.8885135135135135, "c": "red", "max": 472}, {"n": "Quebec, Capitale-Nationale, CA", "id": "2403", "v": 0.9546817727424192, "c": "red", "max": 2016}, {"n": "Quebec, Chaudi\u00e8re-Appalaches, CA", "id": "2412", "v": 0.42377260981912146, "c": "orange", "max": 768}, {"n": "Quebec, C\u00f4te-Nord, CA", "id": "2409", "v": 0.2650602409638554, "c": "yellow", "max": 12}, {"n": "Quebec, Estrie, CA", "id": "2405", "v": 0.13109619686800894, "c": "yellow", "max": 256}, {"n": "Quebec, Gasp\u00e9sie-\u00celes-de-la-Madeleine, CA", "id": "2411", "v": 0.05298013245033112, "c": "green", "max": 9}, {"n": "Quebec, Lanaudi\u00e8re, CA", "id": "2414", "v": 0.16922500935979035, "c": "yellow", "max": 468}, {"n": "Quebec, Laurentides, CA", "id": "2415", "v": 0.23393939393939392, "c": "yellow", "max": 641}, {"n": "Quebec, Laval, CA", "id": "2413", "v": 0.24104953408533594, "c": "yellow", "max": 1190}, {"n": "Quebec, Mauricie, CA", "id": "2404", "v": 0.13288170922355394, "c": "yellow", "max": 275}, {"n": "Quebec, Montr\u00e9al, CA", "id": "2406", "v": 0.28024117573169205, "c": "yellow", "max": 4544}, {"n": "Quebec, Mont\u00e9r\u00e9gie, CA", "id": "2416", "v": 0.21107423053711527, "c": "yellow", "max": 1444}, {"n": "Quebec, Nord-du-Qu\u00e9bec, CA", "id": "2410", "v": 0.04878048780487805, "c": "green", "max": 1}, {"n": "Quebec, Nunavik, CA", "id": "2417", "v": 0.0, "c": "green", "max": 0}, {"n": "Quebec, Outaouais, CA", "id": "2407", "v": 0.9889655172413794, "c": "red", "max": 1172}, {"n": "Quebec, Saguenay, CA", "id": "2402", "v": 0.13274336283185842, "c": "yellow", "max": 387}, {"n": "Quebec, Terres-Cries-de-la-Baie-James, CA", "id": "2418", "v": 0.0, "c": "green", "max": 0}, {"n": "Saskatchewan, Central, CA", "id": "4705", "v": 0.5358490566037736, "c": "orange", "max": 141}, {"n": "Saskatchewan, Far North, CA", "id": "4713", "v": 0.07106598984771574, "c": "yellow", "max": 83}, {"n": "Saskatchewan, North, CA", "id": "4711", "v": 0.1933240611961057, "c": "yellow", "max": 328}, {"n": "Saskatchewan, Regina, CA", "id": "4704", "v": 0.9148936170212766, "c": "red", "max": 1500}, {"n": "Saskatchewan, Saskatoon, CA", "id": "4706", "v": 0.270509977827051, "c": "yellow", "max": 366}, {"n": "Saskatchewan, South, CA", "id": "4701", "v": 0.944153577661431, "c": "red", "max": 476}, {"n": "Yukon, Yukon, CA", "id": "6001", "v": 0.0625, "c": "green", "max": 2}]