[{"n": "01", "id": "01", "v": 0.4621853128590828, "c": "orange", "max": 16844, "date": "11/14/20"}, {"n": "02", "id": "02", "v": 0.6730606488011283, "c": "orange", "max": 5746}, {"n": "03", "id": "03", "v": 0.6004337671004337, "c": "orange", "max": 6042}, {"n": "04", "id": "04", "v": 0.6180589087397392, "c": "orange", "max": 2319}, {"n": "05", "id": "05", "v": 0.5257548845470692, "c": "orange", "max": 3156}, {"n": "06", "id": "06", "v": 0.6068982796058126, "c": "orange", "max": 12555}, {"n": "07", "id": "07", "v": 0.4826201357152749, "c": "orange", "max": 6246}, {"n": "08", "id": "08", "v": 0.633200094051258, "c": "orange", "max": 4520}, {"n": "09", "id": "09", "v": 0.3137847642079806, "c": "yellow", "max": 1105}, {"n": "10", "id": "10", "v": 0.5184026942506615, "c": "orange", "max": 3753}, {"n": "11", "id": "11", "v": 0.5416721182781631, "c": "orange", "max": 3775}, {"n": "12", "id": "12", "v": 0.43670886075949367, "c": "orange", "max": 3338}, {"n": "13", "id": "13", "v": 0.44414922313336214, "c": "orange", "max": 31003}, {"n": "14", "id": "14", "v": 0.46095751854349293, "c": "orange", "max": 5972}, {"n": "15", "id": "15", "v": 0.5904217298070049, "c": "orange", "max": 1388}, {"n": "16", "id": "16", "v": 0.7055971793741737, "c": "orange", "max": 2584}, {"n": "17", "id": "17", "v": 0.48958333333333326, "c": "orange", "max": 2374}, {"n": "18", "id": "18", "v": 0.5677014132141563, "c": "orange", "max": 4122}, {"n": "19", "id": "19", "v": 0.6656277827248441, "c": "orange", "max": 2394}, {"n": "21", "id": "21", "v": 0.5690595436839176, "c": "orange", "max": 9093}, {"n": "22", "id": "22", "v": 0.6409163558870539, "c": "orange", "max": 4140}, {"n": "23", "id": "23", "v": 0.6561712846347607, "c": "orange", "max": 1670}, {"n": "24", "id": "24", "v": 0.5337595907928389, "c": "orange", "max": 3696}, {"n": "25", "id": "25", "v": 0.6267456622936944, "c": "orange", "max": 12856}, {"n": "26", "id": "26", "v": 0.4835516361907231, "c": "orange", "max": 10482}, {"n": "27", "id": "27", "v": 0.5676816400361773, "c": "orange", "max": 6500}, {"n": "28", "id": "28", "v": 0.560174552135967, "c": "orange", "max": 4176}, {"n": "29", "id": "29", "v": 0.43833780160857905, "c": "orange", "max": 4442}, {"n": "2A", "id": "2A", "v": 0.26178234790059984, "c": "yellow", "max": 1476}, {"n": "2B", "id": "2B", "v": 0.37527839643652566, "c": "yellow", "max": 1312}, {"n": "30", "id": "30", "v": 0.4869432203081182, "c": "orange", "max": 11823}, {"n": "31", "id": "31", "v": 0.4288454727895171, "c": "orange", "max": 12790}, {"n": "32", "id": "32", "v": 0.6324614352783366, "c": "orange", "max": 1647}, {"n": "33", "id": "33", "v": 0.5804311107536395, "c": "orange", "max": 12609}, {"n": "34", "id": "34", "v": 0.5033708541503642, "c": "orange", "max": 14691}, {"n": "35", "id": "35", "v": 0.5262604037118531, "c": "orange", "max": 9736}, {"n": "36", "id": "36", "v": 0.7427385892116182, "c": "orange", "max": 2260}, {"n": "37", "id": "37", "v": 0.47267335122157883, "c": "orange", "max": 6082}, {"n": "38", "id": "38", "v": 0.5275734015772124, "c": "orange", "max": 34197}, {"n": "39", "id": "39", "v": 0.5577793247476505, "c": "orange", "max": 5520}, {"n": "40", "id": "40", "v": 0.6467167433971407, "c": "orange", "max": 4630}, {"n": "41", "id": "41", "v": 0.5613577023498695, "c": "orange", "max": 2928}, {"n": "42", "id": "42", "v": 0.49274193548387096, "c": "orange", "max": 24369}, {"n": "43", "id": "43", "v": 0.47763963629615885, "c": "orange", "max": 7250}, {"n": "44", "id": "44", "v": 0.5248601420579546, "c": "orange", "max": 14654}, {"n": "45", "id": "45", "v": 0.5351462792067544, "c": "orange", "max": 9618}, {"n": "46", "id": "46", "v": 0.67825311942959, "c": "orange", "max": 1275}, {"n": "47", "id": "47", "v": 0.7588919288645691, "c": "orange", "max": 3556}, {"n": "48", "id": "48", "v": 0.5465924895688455, "c": "orange", "max": 1496}, {"n": "49", "id": "49", "v": 0.5159825813026961, "c": "orange", "max": 10066}, {"n": "50", "id": "50", "v": 0.5638725641818745, "c": "orange", "max": 3248}, {"n": "51", "id": "51", "v": 0.46698412698412695, "c": "orange", "max": 5244}, {"n": "52", "id": "52", "v": 0.6997491938373342, "c": "orange", "max": 3252}, {"n": "53", "id": "53", "v": 0.621606334841629, "c": "orange", "max": 3416}, {"n": "54", "id": "54", "v": 0.49941805099989417, "c": "orange", "max": 8491}, {"n": "55", "id": "55", "v": 0.60675, "c": "orange", "max": 2116}, {"n": "56", "id": "56", "v": 0.6365135453474676, "c": "orange", "max": 4490}, {"n": "57", "id": "57", "v": 0.6050847457627119, "c": "orange", "max": 14818}, {"n": "58", "id": "58", "v": 0.5810451727192205, "c": "orange", "max": 2277}, {"n": "59", "id": "59", "v": 0.41061719992719276, "c": "orange", "max": 47092}, {"n": "60", "id": "60", "v": 0.5168425495989869, "c": "orange", "max": 11180}, {"n": "61", "id": "61", "v": 0.6894022735606894, "c": "orange", "max": 2958}, {"n": "62", "id": "62", "v": 0.5488352294714032, "c": "orange", "max": 25013}, {"n": "63", "id": "63", "v": 0.5349784818240089, "c": "orange", "max": 10250}, {"n": "64", "id": "64", "v": 0.4942022471910112, "c": "orange", "max": 10127}, {"n": "65", "id": "65", "v": 0.7299554565701559, "c": "orange", "max": 4153}, {"n": "66", "id": "66", "v": 0.37688002798181186, "c": "yellow", "max": 3940}, {"n": "67", "id": "67", "v": 0.42992675613233056, "c": "orange", "max": 17003}, {"n": "68", "id": "68", "v": 0.6024060449393518, "c": "orange", "max": 10705}, {"n": "69", "id": "69", "v": 0.4604348969091524, "c": "orange", "max": 47290}, {"n": "70", "id": "70", "v": 0.6783343391671697, "c": "orange", "max": 3752}, {"n": "71", "id": "71", "v": 0.5040747842761266, "c": "orange", "max": 11703}, {"n": "72", "id": "72", "v": 0.6577277379733879, "c": "orange", "max": 5290}, {"n": "73", "id": "73", "v": 0.5338949323427965, "c": "orange", "max": 14438}, {"n": "74", "id": "74", "v": 0.5528176264671563, "c": "orange", "max": 28742}, {"n": "75", "id": "75", "v": 0.2743915709695178, "c": "yellow", "max": 20847}, {"n": "76", "id": "76", "v": 0.49929659306379587, "c": "orange", "max": 14756}, {"n": "77", "id": "77", "v": 0.5284105062135009, "c": "orange", "max": 16529}, {"n": "78", "id": "78", "v": 0.40315570672713524, "c": "orange", "max": 15736}, {"n": "79", "id": "79", "v": 0.5830721003134797, "c": "orange", "max": 3512}, {"n": "80", "id": "80", "v": 0.6041705804997183, "c": "orange", "max": 5444}, {"n": "81", "id": "81", "v": 0.49535265172225257, "c": "orange", "max": 5002}, {"n": "82", "id": "82", "v": 0.49415692821368956, "c": "orange", "max": 2862}, {"n": "83", "id": "83", "v": 0.49328180737217603, "c": "orange", "max": 15302}, {"n": "84", "id": "84", "v": 0.5014937589523225, "c": "orange", "max": 11094}, {"n": "85", "id": "85", "v": 0.566347144102036, "c": "orange", "max": 6212}, {"n": "86", "id": "86", "v": 0.5500578034682081, "c": "orange", "max": 4178}, {"n": "87", "id": "87", "v": 0.45733623398598017, "c": "orange", "max": 3332}, {"n": "88", "id": "88", "v": 0.5983640081799592, "c": "orange", "max": 5100}, {"n": "89", "id": "89", "v": 0.628822629969419, "c": "orange", "max": 5482}, {"n": "90", "id": "90", "v": 0.7264378927017884, "c": "orange", "max": 2480}, {"n": "91", "id": "91", "v": 0.43303258015028995, "c": "orange", "max": 15439}, {"n": "92", "id": "92", "v": 0.3414101031235989, "c": "yellow", "max": 17445}, {"n": "93", "id": "93", "v": 0.4176799400679998, "c": "orange", "max": 20248}, {"n": "94", "id": "94", "v": 0.4094111450080109, "c": "orange", "max": 17352}, {"n": "95", "id": "95", "v": 0.3882086771360128, "c": "yellow", "max": 16160}, {"n": "971", "id": "971", "v": 0.10140148392415499, "c": "yellow", "max": 628}, {"n": "972", "id": "972", "v": 0.4752851711026616, "c": "orange", "max": 1748}, {"n": "973", "id": "973", "v": 0.1051150895140665, "c": "yellow", "max": 584}, {"n": "974", "id": "974", "v": 0.8574348492590701, "c": "red", "max": 2556}, {"n": "975", "id": "975", "v": 0.0, "c": "green", "max": 0}, {"n": "976", "id": "976", "v": 0.753071253071253, "c": "orange", "max": 982}, {"n": "977", "id": "977", "v": 0.9310344827586208, "c": "red", "max": 66}, {"n": "978", "id": "978", "v": 0.5608465608465608, "c": "orange", "max": 156}]