[{"n": "Bansk\u00e1 Bystrica", "id": "Bansk\u00e1 Bystrica", "v": 0.0886844845539743, "c": "yellow", "max": 657, "date": "04/29/21"}, {"n": "Bratislava", "id": "Bratislava", "v": 0.05231938149826713, "c": "yellow", "max": 509}, {"n": "Ko\u0161ice", "id": "Ko\u0161ice", "v": 0.12954296524942746, "c": "yellow", "max": 972}, {"n": "NOT SPECIFIED", "id": "NOT SPECIFIED", "v": 0.0, "c": "green", "max": 0}, {"n": "Nitra", "id": "Nitra", "v": 0.06493506493506493, "c": "yellow", "max": 425}, {"n": "Pre\u0161ov", "id": "Pre\u0161ov", "v": 0.16895020315600492, "c": "yellow", "max": 1203}, {"n": "Trenc\u00edn", "id": "Trenc\u00edn", "v": 0.1465665889035399, "c": "yellow", "max": 952}, {"n": "Trnava", "id": "Trnava", "v": 0.08987648875165417, "c": "yellow", "max": 559}, {"n": "Zilina", "id": "Zilina", "v": 0.15360553177477773, "c": "yellow", "max": 1317}]