[{"n": "Baranya", "id": "Baranya", "v": 0.6043246279135074, "c": "orange", "max": 1481, "date": "1/2/21"}, {"n": "Borsod-Aba\u00faj-Zempl\u00e9n", "id": "Borsod-Aba\u00faj-Zempl\u00e9n", "v": 0.1875246224556796, "c": "yellow", "max": 965}, {"n": "Budapest", "id": "Budapest", "v": 0.2377799900447984, "c": "yellow", "max": 3350}, {"n": "B\u00e1cs-Kiskun", "id": "B\u00e1cs-Kiskun", "v": 0.31999357119897137, "c": "yellow", "max": 1371}, {"n": "B\u00e9k\u00e9s", "id": "B\u00e9k\u00e9s", "v": 0.1932327085752198, "c": "yellow", "max": 860}, {"n": "Csongr\u00e1d", "id": "Csongr\u00e1d", "v": 0.33681180280676504, "c": "yellow", "max": 1308}, {"n": "Fej\u00e9r", "id": "Fej\u00e9r", "v": 0.39300202839756593, "c": "yellow", "max": 1075}, {"n": "Gy\u0151r-Moson-Sopron", "id": "Gy\u0151r-Moson-Sopron", "v": 0.15154879538137003, "c": "yellow", "max": 945}, {"n": "Hajd\u00fa-Bihar", "id": "Hajd\u00fa-Bihar", "v": 0.3291587258371903, "c": "yellow", "max": 1693}, {"n": "Heves", "id": "Heves", "v": 0.2520760782212697, "c": "yellow", "max": 681}, {"n": "Hungary", "id": "Hungary", "v": 0, "c": "darkgreen", "max": 0}, {"n": "J\u00e1sz-Nagykun-Szolnok", "id": "J\u00e1sz-Nagykun-Szolnok", "v": 0.30263653483992464, "c": "yellow", "max": 1125}, {"n": "Kom\u00e1rom-Esztergom", "id": "Kom\u00e1rom-Esztergom", "v": 0.23634396971335858, "c": "yellow", "max": 648}, {"n": "NOT SPECIFIED", "id": "NOT SPECIFIED", "v": 0.0, "c": "green", "max": 0}, {"n": "N\u00f3gr\u00e1d", "id": "N\u00f3gr\u00e1d", "v": 0.2744822744822745, "c": "yellow", "max": 566}, {"n": "Pest", "id": "Pest", "v": 0.23665680890015492, "c": "yellow", "max": 2435}, {"n": "Somogy", "id": "Somogy", "v": 0.4233496999454446, "c": "orange", "max": 1171}, {"n": "Szabolcs-Szatm\u00e1r-Bereg", "id": "Szabolcs-Szatm\u00e1r-Bereg", "v": 0.2416773367477593, "c": "yellow", "max": 1071}, {"n": "Tolna", "id": "Tolna", "v": 0.2832786885245902, "c": "yellow", "max": 596}, {"n": "Vas", "id": "Vas", "v": 0.20314419061655611, "c": "yellow", "max": 616}, {"n": "Veszpr\u00e9m", "id": "Veszpr\u00e9m", "v": 0.2926926131850675, "c": "yellow", "max": 1042}, {"n": "Zala", "id": "Zala", "v": 0.28885832187070154, "c": "yellow", "max": 700}]